[{"__symbolic":"module","version":3,"metadata":{"AppModule":{"__symbolic":"class","decorators":[{"__symbolic":"call","expression":{"__symbolic":"reference","module":"@angular/core","name":"NgModule"},"arguments":[{"declarations":[{"__symbolic":"reference","module":"./app.component","name":"AppComponent"},{"__symbolic":"reference","module":"./header/header.component","name":"HeaderComponent"},{"__symbolic":"reference","module":"./welcome/welcome.component","name":"WelcomeComponent"},{"__symbolic":"reference","module":"./health/health.component","name":"HealthComponent"},{"__symbolic":"reference","module":"./nutrition/nutrition.component","name":"NutritionComponent"},{"__symbolic":"reference","module":"./fitness/fitness.component","name":"FitnessComponent"},{"__symbolic":"reference","module":"./about/about.component","name":"AboutComponent"}],"imports":[{"__symbolic":"reference","module":"@angular/platform-browser","name":"BrowserModule"},{"__symbolic":"reference","module":"@angular/forms","name":"FormsModule"},{"__symbolic":"reference","module":"@angular/http","name":"HttpModule"},{"__symbolic":"call","expression":{"__symbolic":"select","expression":{"__symbolic":"reference","module":"@angular/router","name":"RouterModule"},"member":"forRoot"},"arguments":[[{"path":"welcome","component":{"__symbolic":"reference","module":"./welcome/welcome.component","name":"WelcomeComponent"}},{"path":"health","component":{"__symbolic":"reference","module":"./health/health.component","name":"HealthComponent"}},{"path":"nutrition","component":{"__symbolic":"reference","module":"./nutrition/nutrition.component","name":"NutritionComponent"}},{"path":"fitness","component":{"__symbolic":"reference","module":"./fitness/fitness.component","name":"FitnessComponent"}},{"path":"about","component":{"__symbolic":"reference","module":"./about/about.component","name":"AboutComponent"}},{"path":"","redirectTo":"/welcome","pathMatch":"full"},{"path":"**","redirectTo":"/welcome"}],{"useHash":false}]}],"providers":[{"__symbolic":"reference","module":"./route-index.service","name":"RouteIndexService"}],"bootstrap":[{"__symbolic":"reference","module":"./app.component","name":"AppComponent"}]}]}]}}},{"__symbolic":"module","version":1,"metadata":{"AppModule":{"__symbolic":"class","decorators":[{"__symbolic":"call","expression":{"__symbolic":"reference","module":"@angular/core","name":"NgModule"},"arguments":[{"declarations":[{"__symbolic":"reference","module":"./app.component","name":"AppComponent"},{"__symbolic":"reference","module":"./header/header.component","name":"HeaderComponent"},{"__symbolic":"reference","module":"./welcome/welcome.component","name":"WelcomeComponent"},{"__symbolic":"reference","module":"./health/health.component","name":"HealthComponent"},{"__symbolic":"reference","module":"./nutrition/nutrition.component","name":"NutritionComponent"},{"__symbolic":"reference","module":"./fitness/fitness.component","name":"FitnessComponent"},{"__symbolic":"reference","module":"./about/about.component","name":"AboutComponent"}],"imports":[{"__symbolic":"reference","module":"@angular/platform-browser","name":"BrowserModule"},{"__symbolic":"reference","module":"@angular/forms","name":"FormsModule"},{"__symbolic":"reference","module":"@angular/http","name":"HttpModule"},{"__symbolic":"call","expression":{"__symbolic":"select","expression":{"__symbolic":"reference","module":"@angular/router","name":"RouterModule"},"member":"forRoot"},"arguments":[[{"path":"welcome","component":{"__symbolic":"reference","module":"./welcome/welcome.component","name":"WelcomeComponent"}},{"path":"health","component":{"__symbolic":"reference","module":"./health/health.component","name":"HealthComponent"}},{"path":"nutrition","component":{"__symbolic":"reference","module":"./nutrition/nutrition.component","name":"NutritionComponent"}},{"path":"fitness","component":{"__symbolic":"reference","module":"./fitness/fitness.component","name":"FitnessComponent"}},{"path":"about","component":{"__symbolic":"reference","module":"./about/about.component","name":"AboutComponent"}},{"path":"","redirectTo":"/welcome","pathMatch":"full"},{"path":"**","redirectTo":"/welcome"}],{"useHash":false}]}],"providers":[{"__symbolic":"reference","module":"./route-index.service","name":"RouteIndexService"}],"bootstrap":[{"__symbolic":"reference","module":"./app.component","name":"AppComponent"}]}]}]}}}]